.bumpversion.cfg
.cookiecutterrc
.coveragerc
.editorconfig
.travis.yml
AUTHORS.rst
CHANGELOG.rst
CONTRIBUTING.rst
LICENSE
MANIFEST.in
README.rst
setup.cfg
setup.py
tox.ini
ci/bootstrap.py
ci/templates/.travis.yml
docs/authors.rst
docs/changelog.rst
docs/conf.py
docs/contributing.rst
docs/index.rst
docs/installation.rst
docs/readme.rst
docs/requirements.txt
docs/spelling_wordlist.txt
docs/usage.rst
docs/_build_html/.buildinfo
docs/_build_html/authors.html
docs/_build_html/changelog.html
docs/_build_html/contributing.html
docs/_build_html/genindex.html
docs/_build_html/index.html
docs/_build_html/installation.html
docs/_build_html/objects.inv
docs/_build_html/py-modindex.html
docs/_build_html/readme.html
docs/_build_html/search.html
docs/_build_html/searchindex.js
docs/_build_html/usage.html
docs/_build_html/.doctrees/authors.doctree
docs/_build_html/.doctrees/changelog.doctree
docs/_build_html/.doctrees/contributing.doctree
docs/_build_html/.doctrees/environment.pickle
docs/_build_html/.doctrees/index.doctree
docs/_build_html/.doctrees/installation.doctree
docs/_build_html/.doctrees/readme.doctree
docs/_build_html/.doctrees/usage.doctree
docs/_build_html/.doctrees/reference/index.doctree
docs/_build_html/.doctrees/reference/toba.doctree
docs/_build_html/_sources/authors.rst.txt
docs/_build_html/_sources/changelog.rst.txt
docs/_build_html/_sources/contributing.rst.txt
docs/_build_html/_sources/index.rst.txt
docs/_build_html/_sources/installation.rst.txt
docs/_build_html/_sources/readme.rst.txt
docs/_build_html/_sources/usage.rst.txt
docs/_build_html/_sources/reference/index.rst.txt
docs/_build_html/_sources/reference/toba.rst.txt
docs/_build_html/_static/ajax-loader.gif
docs/_build_html/_static/basic.css
docs/_build_html/_static/comment-bright.png
docs/_build_html/_static/comment-close.png
docs/_build_html/_static/comment.png
docs/_build_html/_static/doctools.js
docs/_build_html/_static/down-pressed.png
docs/_build_html/_static/down.png
src/toba.egg-info/PKG-INFO
src/toba.egg-info/SOURCES.txt
src/toba.egg-info/dependency_links.txt
src/toba.egg-info/entry_points.txt
src/toba.egg-info/not-zip-safe
src/toba.egg-info/requires.txt
src/toba.egg-info/top_level.txt
