Metadata-Version: 1.1
Name: toba
Version: 0.1.1
Summary: Timeliness Ordered Byzantine Agreement
Home-page: https://smithsamuelm@bitbucket.org/prosapien/toba.git
Author: Samuel M. Smith
Author-email: sam@prosapien.com
License: Apache2
Keywords: Timeliness Ordered Byzantine Agreement,BFT,Ansynchronous
Platform: UNKNOWN
Classifier: Development Status :: 1 - Planning
Classifier: Intended Audience :: Developers
Classifier: License :: OSI Approved :: Apache Software License
Classifier: Operating System :: Unix
Classifier: Operating System :: POSIX
Classifier: Operating System :: Microsoft :: Windows
Classifier: Programming Language :: Python
Classifier: Programming Language :: Python :: 3.6
Classifier: Programming Language :: Python :: Implementation :: CPython
Classifier: Programming Language :: Python :: Implementation :: PyPy
Classifier: Topic :: Utilities
